Workbook

Sheet README
A1: Consolidated segment data: Bajaj Finance and Mahindra Finance (FY2016-17 to FY2025-26)
A3: Scope: consolidated-level segment data only. Bajaj rows are the consolidated rows of master_nbfc_dataset_full.csv (standalone rows excluded). Mahindra data are the consolidated Loans-note product split from Mahindra_Finance_Consolidated_10yr_Dataset.xlsx (sheet Segment_AUM).
A4: Mahindra vehicle-wise split (UV, cars, tractors, CV, pre-owned) exists only for the standalone company, so it is excluded.
A5: Units: Rs crore; years end 31 March. Percentages are stored as fractions and displayed as %.
A7: Colour code: blue = value copied from the source files; black = formula; green = link to another sheet.
A9: What each segment source offers
A10: Mahindra: product-level AUM (retail, housing, SME, bills, trade advances, finance lease, other) for FY2017-18 to FY2025-26. FY2016-17 product split was not extracted in the source (left blank).
A11: Bajaj: the source provides only a high / medium / low risk-tier share and a secured / unsecured share of the book, not product-level amounts. Rupee amounts in Bajaj_Segments are derived (share x AUM) and marked as such.
A13: Comparability warnings
A14: 1. Bajaj segment taxonomy changes: FY17-FY18 = 5 segments (taxonomy 0, flagged not comparable); FY19-FY22 = 10 (A); FY23-FY24 = 11 (B); FY25-FY26 = 14 (C). The large jump in Bajaj secured share between FY18 and FY19 reflects the reclassification, not a business change. Use FY19 onward for trends.
A15: 2. The source file does not document how Bajaj risk tiers or the secured / unsecured split are defined, so treat them as the dataset compiler's classification, not a company-reported figure.
A16: 3. Mahindra secured = retail + housing finance + finance lease, following the source file's own product classification (Product_Tiers sheet). SME + bills are labelled "mixed" and trade advances "mostly unsecured" there; they are grouped as unsecured / mixed here.
... A18: 5. Mahindra Total (calc) is checked against the master-dataset AUM in column K of Mahindra_Product_Mix; differences are rounding.

Sheet Mahindra_Product_Mix
A1: Mahindra Finance: consolidated gross loans by product (Rs crore) and share of book
A2: Source: Mahindra Finance annual reports, consolidated Loans note, via Segment_AUM sheet of the provided file. Housing finance = Mahindra Rural Housing Finance (subsidiary).
A4: Financial year | B4: Retail loans | C4: Housing finance | D4: SME financing | E4: Bills of exchange | F4: Trade advances | G4: Finance lease | H4: Inter-corporate deposits & other | I4: Total (Rs Cr) | J4: AUM per master dataset (Rs Cr) | K4: Difference (total - AUM) | L4: Retail % | M4: Housing % | N4: SME + bills % | O4: Trade advances % | P4: Finance lease % | Q4: Secured % (retail + housing + lease) | R4: Unsecured / mixed % | S4: Source
A5: FY2016-17 | I5: =IF(COUNT(B5:H5)=0,"",SUM(B5:H5)) | J5: 47994.47 | K5: =IF(I5="","",I5-J5) | L5: =IF($I5="","",B5/$I5) | M5: =IF($I5="","",C5/$I5) | N5: =IF($I5="","",(D5+E5)/$I5) | O5: =IF($I5="","",F5/$I5) | P5: =IF($I5="","",G5/$I5) | Q5: =IF($I5="","",(B5+C5+G5)/$I5) | R5: =IF(Q5="","",1-Q5) | S5: AR 2016-17 – product split not extracted (IGAAP notes show loans against assets / trade advances)
A6: FY2017-18 | B6: 48169.6 | C6: 6312.17 | D6: 1360.49 | E6: 550.32 | F6: 1437.27 | G6: 0 | H6: 2.67 | I6: =IF(COUNT(B6:H6)=0,"",SUM(B6:H6)) -> 57832.52 | J6: 57832.53 | K6: =IF(I6="","",I6-J6) -> -0.01 | L6: =IF($I6="","",B6/$I6) -> 0.83291546 | M6: =IF($I6="","",C6/$I6) -> 0.10914568 | N6: =IF($I6="","",(D6+E6)/$I6) -> 0.033040407 | O6: =IF($I6="","",F6/$I6) -> 0.02485228 | P6: =IF($I6="","",G6/$I6) -> 0 | Q6: =IF($I6="","",(B6+C6+G6)/$I6) -> 0.94206114 | R6: =IF(Q6="","",1-Q6) -> 0.057938855 | S6: AR 2018-19 (FY18 Ind AS comparatives) note 7 p.268
A7: FY2018-19 | B7: 58741.47 | C7: 8048.75 | D7: 1880.53 | E7: 615.35 | F7: 1874.31 | G7: 0 | H7: 1.12 | I7: =IF(COUNT(B7:H7)=0,"",SUM(B7:H7)) -> 71161.53 | J7: 71161.53 | K7: =IF(I7="","",I7-J7) -> 0 | L7: =IF($I7="","",B7/$I7) -> 0.82546665 | M7: =IF($I7="","",C7/$I7) -> 0.11310535 | N7: =IF($I7="","",(D7+E7)/$I7) -> 0.035073445 | O7: =IF($I7="","",F7/$I7) -> 0.02633881 | P7: =IF($I7="","",G7/$I7) -> 0 | Q7: =IF($I7="","",(B7+C7+G7)/$I7) -> 0.93857201 | R7: =IF(Q7="","",1-Q7) -> 0.061427993 | S7: AR 2018-19 note 7 p.268
A8: FY2019-20 | B8: 64439.78 | C8: 8443.89 | D8: 1864.41 | E8: 531.66 | F8: 1239.35 | G8: 0 | H8: 1.23 | I8: =IF(COUNT(B8:H8)=0,"",SUM(B8:H8)) -> 76520.32 | J8: 76520.33 | K8: =IF(I8="","",I8-J8) -> -0.01 | L8: =IF($I8="","",B8/$I8) -> 0.84212638 | M8: =IF($I8="","",C8/$I8) -> 0.11034834 | N8: =IF($I8="","",(D8+E8)/$I8) -> 0.031312859 | O8: =IF($I8="","",F8/$I8) -> 0.016196352 | P8: =IF($I8="","",G8/$I8) -> 0 | Q8: =IF($I8="","",(B8+C8+G8)/$I8) -> 0.95247472 | R8: =IF(Q8="","",1-Q8) -> 0.047525285 | S8: AR 2019-20 note 7 p.295
A9: FY2020-21 | B9: 61638.86 | C9: 7646.71 | D9: 1014.73 | E9: 743.1 | F9: 1194.98 | G9: 0 | H9: 1.19 | I9: =IF(COUNT(B9:H9)=0,"",SUM(B9:H9)) -> 72239.57 | J9: 72239.57 | K9: =IF(I9="","",I9-J9) -> 0 | L9: =IF($I9="","",B9/$I9) -> 0.85325619 | M9: =IF($I9="","",C9/$I9) -> 0.1058521 | N9: =IF($I9="","",(D9+E9)/$I9) -> 0.02433334 | O9: =IF($I9="","",F9/$I9) -> 0.016541904 | P9: =IF($I9="","",G9/$I9) -> 0 | Q9: =IF($I9="","",(B9+C9+G9)/$I9) -> 0.95910828 | R9: =IF(Q9="","",1-Q9) -> 0.040891716 | S9: IAR 2020-21 note 7 p.353
A10: FY2021-22 | B10: 61066.67 | C10: 7603.45 | D10: 1196.15 | E10: 944.33 | F10: 1807.42 | G10: 122.88 | H10: 0.17 | I10: =IF(COUNT(B10:H10)=0,"",SUM(B10:H10)) -> 72741.07 | J10: 72741.07 | K10: =IF(I10="","",I10-J10) -> 0 | L10: =IF($I10="","",B10/$I10) -> 0.83950745 | M10: =IF($I10="","",C10/$I10) -> 0.10452761 | N10: =IF($I10="","",(D10+E10)/$I10) -> 0.029426018 | O10: =IF($I10="","",F10/$I10) -> 0.024847311 | P10: =IF($I10="","",G10/$I10) -> 0.0016892795 | Q10: =IF($I10="","",(B10+C10+G10)/$I10) -> 0.94572433 | R10: =IF(Q10="","",1-Q10) -> 0.054275666 | S10: IR 2021-22 note 7 p.347
A11: FY2022-23 | B11: 75687.27 | C11: 7199.93 | D11: 3481.07 | E11: 975.61 | F11: 2540.42 | G11: 220.95 | H11: 0.11 | I11: =IF(COUNT(B11:H11)=0,"",SUM(B11:H11)) -> 90105.36 | J11: 90105.36 | K11: =IF(I11="","",I11-J11) -> 0 | L11: =IF($I11="","",B11/$I11) -> 0.83998632 | M11: =IF($I11="","",C11/$I11) -> 0.079905679 | N11: =IF($I11="","",(D11+E11)/$I11) -> 0.049460765 | O11: =IF($I11="","",F11/$I11) -> 0.028193883 | P11: =IF($I11="","",G11/$I11) -> 0.0024521294 | Q11: =IF($I11="","",(B11+C11+G11)/$I11) -> 0.92234413 | R11: =IF(Q11="","",1-Q11) -> 0.077655869 | S11: IR 2022-23 note 7 p.437
A12: FY2023-24 | B12: 94410.63 | C12: 7209.08 | D12: 3757.67 | E12: 1054.74 | F12: 2879.1 | G12: 714.52 | H12: 0.08 | I12: =IF(COUNT(B12:H12)=0,"",SUM(B12:H12)) -> 110025.82 | J12: 110025.82 | K12: =IF(I12="","",I12-J12) -> 0 | L12: =IF($I12="","",B12/$I12) -> 0.85807704 | M12: =IF($I12="","",C12/$I12) -> 0.065521711 | N12: =IF($I12="","",(D12+E12)/$I12) -> 0.043738915 | O12: =IF($I12="","",F12/$I12) -> 0.026167494 | P12: =IF($I12="","",G12/$I12) -> 0.006494112 | Q12: =IF($I12="","",(B12+C12+G12)/$I12) -> 0.93009286 | R12: =IF(Q12="","",1-Q12) -> 0.069907136 | S12: IR 2023-24 note 6 p.420
A13: FY2024-25 | B13: 109650.3 | C13: 7503.09 | D13: 4825.83 | E13: 1322.71 | F13: 3199.2 | G13: 1087.23 | H13: 0.05 | I13: =IF(COUNT(B13:H13)=0,"",SUM(B13:H13)) -> 127588.41 | J13: 127588.41 | K13: =IF(I13="","",I13-J13) -> 0 | L13: =IF($I13="","",B13/$I13) -> 0.85940643 | M13: =IF($I13="","",C13/$I13) -> 0.058806987 | N13: =IF($I13="","",(D13+E13)/$I13) -> 0.048190427 | O13: =IF($I13="","",F13/$I13) -> 0.025074378 | P13: =IF($I13="","",G13/$I13) -> 0.0085213853 | Q13: =IF($I13="","",(B13+C13+G13)/$I13) -> 0.9267348 | R13: =IF(Q13="","",1-Q13) -> 0.073265197 | S13: IR 2025-26 (FY25 comparatives) note 7 p.474
A14: FY2025-26 | B14: 122410.36 | C14: 8512.15 | D14: 5740.61 | E14: 2349.51 | F14: 3163.21 | G14: 1229 | H14: 0.3 | I14: =IF(COUNT(B14:H14)=0,"",SUM(B14:H14)) -> 143405.14 | J14: 143405.14 | K14: =IF(I14="","",I14-J14) -> 0 | L14: =IF($I14="","",B14/$I14) -> 0.85359813 | M14: =IF($I14="","",C14/$I14) -> 0.059357356 | N14: =IF($I14="","",(D14+E14)/$I14) -> 0.056414435 | O14: =IF($I14="","",F14/$I14) -> 0.022057857 | P14: =IF($I14="","",G14/$I14) -> 0.0085701252 | Q14: =IF($I14="","",(B14+C14+G14)/$I14) -> 0.92152562 | R14: =IF(Q14="","",1-Q14) -> 0.078474384 | S14: IR 2025-26 note 7 p.474
A16: FY2016-17: product split not extracted in the source file (IGAAP notes show loans against assets / trade advances), so product columns are blank.

Sheet Bajaj_Segments
A1: Bajaj Finance: consolidated segment mix (risk tier and secured / unsecured share of book)
A2: Source: master_nbfc_dataset_full.csv, consolidated rows only. Rupee columns M-Q are derived (share x AUM) and approximate; tier definitions are not documented in the source.
A4: Financial year | B4: Consolidated AUM (Rs Cr) | C4: Segment taxonomy | D4: No. of segments | E4: Comparable with later years? | F4: High-risk tier % | G4: Medium-risk tier % | H4: Low-risk tier % | I4: Tier check (should be 100%) | J4: Secured % | K4: Unsecured % | L4: Secured + unsecured check | M4: High-risk tier (Rs Cr, derived) | N4: Medium-risk tier (Rs Cr, derived) | O4: Low-risk tier (Rs Cr, derived) | P4: Secured (Rs Cr, derived) | Q4: Unsecured (Rs Cr, derived) | R4: Note
A5: FY2016-17 | B5: 60196 | C5: 0 | D5: 5 | E5: No | F5: 0.65007642 | G5: 0.21896804 | H5: 0.13095555 | I5: =SUM(F5:H5) -> 1 | J5: 0.13095555 | K5: 0.86904445 | L5: =J5+K5 -> 1 | M5: =$B5*F5 -> 39132 | N5: =$B5*G5 -> 13181 | O5: =$B5*H5 -> 7883 | P5: =$B5*J5 -> 7883 | Q5: =$B5*K5 -> 52313 | R5: Not comparable: 5-segment taxonomy; excluded from trends
A6: FY2017-18 | B6: 82422 | C6: 0 | D6: 5 | E6: No | F6: 0.6578011 | G6: 0.19493532 | H6: 0.14726358 | I6: =SUM(F6:H6) -> 1 | J6: 0.14726358 | K6: 0.85273642 | L6: =J6+K6 -> 1 | M6: =$B6*F6 -> 54217.282 | N6: =$B6*G6 -> 16066.959 | O6: =$B6*H6 -> 12137.758 | P6: =$B6*J6 -> 12137.758 | Q6: =$B6*K6 -> 70284.242 | R6: Not comparable: 5-segment taxonomy; excluded from trends
A7: FY2018-19 | B7: 115888 | C7: A | D7: 10 | E7: Yes | F7: 0.47967003 | G7: 0.12428379 | H7: 0.39604618 | I7: =SUM(F7:H7) -> 1 | J7: 0.47997204 | K7: 0.52002796 | L7: =J7+K7 -> 1 | M7: =$B7*F7 -> 55588 | N7: =$B7*G7 -> 14403 | O7: =$B7*H7 -> 45897 | P7: =$B7*J7 -> 55623 | Q7: =$B7*K7 -> 60265
A8: FY2019-20 | B8: 147153 | C8: A | D8: 10 | E8: Yes | F8: 0.50579329 | G8: 0.1041501 | H8: 0.39005661 | I8: =SUM(F8:H8) -> 1 | J8: 0.47897766 | K8: 0.52102234 | L8: =J8+K8 -> 1 | M8: =$B8*F8 -> 74429 | N8: =$B8*G8 -> 15326 | O8: =$B8*H8 -> 57398 | P8: =$B8*J8 -> 70483 | Q8: =$B8*K8 -> 76670
A9: FY2020-21 | B9: 152947 | C9: A | D9: 10 | E9: Yes | F9: 0.48775066 | G9: 0.094209105 | H9: 0.41804024 | I9: =SUM(F9:H9) -> 1 | J9: 0.49722453 | K9: 0.50277547 | L9: =J9+K9 -> 1 | M9: =$B9*F9 -> 74600 | N9: =$B9*G9 -> 14409 | O9: =$B9*H9 -> 63938 | P9: =$B9*J9 -> 76049 | Q9: =$B9*K9 -> 76898
A10: FY2021-22 | B10: 197452 | C10: A | D10: 10 | E10: Yes | F10: 0.45198833 | G10: 0.096762758 | H10: 0.45124891 | I10: =SUM(F10:H10) -> 1 | J10: 0.50287665 | K10: 0.49712335 | L10: =J10+K10 -> 1 | M10: =$B10*F10 -> 89246 | N10: =$B10*G10 -> 19106 | O10: =$B10*H10 -> 89100 | P10: =$B10*J10 -> 99294 | Q10: =$B10*K10 -> 98158
A11: FY2022-23 | B11: 247379 | C11: B | D11: 11 | E11: Yes | F11: 0.44767745 | G11: 0.10183969 | H11: 0.45048286 | I11: =SUM(F11:H11) -> 1 | J11: 0.51411801 | K11: 0.48588199 | L11: =J11+K11 -> 1 | M11: =$B11*F11 -> 110746 | N11: =$B11*G11 -> 25193 | O11: =$B11*H11 -> 111440 | P11: =$B11*J11 -> 127182 | Q11: =$B11*K11 -> 120197
A12: FY2023-24 | B12: 330615 | C12: B | D12: 11 | E12: Yes | F12: 0.42923642 | G12: 0.11113833 | H12: 0.45962524 | I12: =SUM(F12:H12) -> 1 | J12: 0.54077401 | K12: 0.45922599 | L12: =J12+K12 -> 1 | M12: =$B12*F12 -> 141912 | N12: =$B12*G12 -> 36744 | O12: =$B12*H12 -> 151959 | P12: =$B12*J12 -> 178788 | Q12: =$B12*K12 -> 151827
A13: FY2024-25 | B13: 416661 | C13: C | D13: 14 | E13: Yes | F13: 0.4045303 | G13: 0.13729147 | H13: 0.45817823 | I13: =SUM(F13:H13) -> 1 | J13: 0.53220004 | K13: 0.46779996 | L13: =J13+K13 -> 1 | M13: =$B13*F13 -> 168552 | N13: =$B13*G13 -> 57204 | O13: =$B13*H13 -> 190905 | P13: =$B13*J13 -> 221747 | Q13: =$B13*K13 -> 194914
A14: FY2025-26 | B14: 509975 | C14: C | D14: 14 | E14: Yes | F14: 0.36820432 | G14: 0.14746997 | H14: 0.4843257 | I14: =SUM(F14:H14) -> 1 | J14: 0.54610324 | K14: 0.45389676 | L14: =J14+K14 -> 1 | M14: =$B14*F14 -> 187775 | N14: =$B14*G14 -> 75206 | O14: =$B14*H14 -> 246994 | P14: =$B14*J14 -> 278499 | Q14: =$B14*K14 -> 231476

Sheet Product_Tiers
A1: Mahindra product classification (source file analyst view)
A3: Product | B3: Secured / unsecured | C3: Risk tier | D3: Why
A4: Retail loans | B4: Secured (vehicle) | C4: Medium–High | D4: Rural/semi-urban vehicle, tractor and pre-owned loans; farm-income dependence
A5: Housing finance | B5: Secured (property) | C5: High | D5: Rural affordable housing; highest Stage 3 ratio of the group's portfolios
A6: SME financing + bills | B6: Mixed | C6: High | D6: Small-business cash flows; bill discounting short tenor
A7: Trade advances | B7: Mostly unsecured | C7: Low–Medium | D7: Short-term dealer/channel finance (~90 days)
A8: Finance lease | B8: Secured (asset) | C8: Medium | D8: Vehicle leasing
A10: Bajaj tiers: the source gives only high / medium / low shares without product definitions.

Sheet Secured_Comparison
A1: Secured share of book: Bajaj vs Mahindra (consolidated)
A3: Financial year | B3: Bajaj secured % (comparable years only) | C3: Mahindra secured % | D3: Gap (Mahindra - Bajaj)
A4: FY2016-17 | B4: =IF(Bajaj_Segments!E5="Yes",Bajaj_Segments!J5,"") | C4: =Mahindra_Product_Mix!Q5 | D4: =IF(OR(B4="",C4=""),"",C4-B4)
A5: FY2017-18 | B5: =IF(Bajaj_Segments!E6="Yes",Bajaj_Segments!J6,"") | C5: =Mahindra_Product_Mix!Q6 -> 0.94206114 | D5: =IF(OR(B5="",C5=""),"",C5-B5)
A6: FY2018-19 | B6: =IF(Bajaj_Segments!E7="Yes",Bajaj_Segments!J7,"") -> 0.47997204 | C6: =Mahindra_Product_Mix!Q7 -> 0.93857201 | D6: =IF(OR(B6="",C6=""),"",C6-B6) -> 0.45859996
A7: FY2019-20 | B7: =IF(Bajaj_Segments!E8="Yes",Bajaj_Segments!J8,"") -> 0.47897766 | C7: =Mahindra_Product_Mix!Q8 -> 0.95247472 | D7: =IF(OR(B7="",C7=""),"",C7-B7) -> 0.47349705
A8: FY2020-21 | B8: =IF(Bajaj_Segments!E9="Yes",Bajaj_Segments!J9,"") -> 0.49722453 | C8: =Mahindra_Product_Mix!Q9 -> 0.95910828 | D8: =IF(OR(B8="",C8=""),"",C8-B8) -> 0.46188375
A9: FY2021-22 | B9: =IF(Bajaj_Segments!E10="Yes",Bajaj_Segments!J10,"") -> 0.50287665 | C9: =Mahindra_Product_Mix!Q10 -> 0.94572433 | D9: =IF(OR(B9="",C9=""),"",C9-B9) -> 0.44284769
A10: FY2022-23 | B10: =IF(Bajaj_Segments!E11="Yes",Bajaj_Segments!J11,"") -> 0.51411801 | C10: =Mahindra_Product_Mix!Q11 -> 0.92234413 | D10: =IF(OR(B10="",C10=""),"",C10-B10) -> 0.40822612
A11: FY2023-24 | B11: =IF(Bajaj_Segments!E12="Yes",Bajaj_Segments!J12,"") -> 0.54077401 | C11: =Mahindra_Product_Mix!Q12 -> 0.93009286 | D11: =IF(OR(B11="",C11=""),"",C11-B11) -> 0.38931885
A12: FY2024-25 | B12: =IF(Bajaj_Segments!E13="Yes",Bajaj_Segments!J13,"") -> 0.53220004 | C12: =Mahindra_Product_Mix!Q13 -> 0.9267348 | D12: =IF(OR(B12="",C12=""),"",C12-B12) -> 0.39453477
A13: FY2025-26 | B13: =IF(Bajaj_Segments!E14="Yes",Bajaj_Segments!J14,"") -> 0.54610324 | C13: =Mahindra_Product_Mix!Q14 -> 0.92152562 | D13: =IF(OR(B13="",C13=""),"",C13-B13) -> 0.37542238
A15: Bajaj FY17-FY18 blanked (taxonomy not comparable). Mahindra FY17 blank (product split not extracted).
